ratingcurve/__init__.py
ratingcurve/_version.py
ratingcurve/experimental_ratings.py
ratingcurve/model_builder.py
ratingcurve/plot.py
ratingcurve/ratingmodel_builder.py
ratingcurve/ratings.py
ratingcurve/transform.py
ratingcurve/data/__init__.py
ratingcurve/data/chalk_artificial.csv
ratingcurve/data/chalk_artificial.md
ratingcurve/data/co_channel.csv
ratingcurve/data/co_channel.md
ratingcurve/data/green_channel.csv
ratingcurve/data/green_channel.md
ratingcurve/data/isere.csv
ratingcurve/data/isere.md
ratingcurve/data/mahurangi_artificial.csv
ratingcurve/data/mahurangi_artificial.md
ratingcurve/data/nordura.csv
ratingcurve/data/nordura.md
ratingcurve/data/provo_natural.csv
ratingcurve/data/provo_natural.md
ratingcurve/data/simulated_rating.csv
ratingcurve/data/simulated_rating.md
ratingcurve/data/skajalfandafljot.csv
ratingcurve/data/skajalfandafljot.md
ratingcurve/tests/__init__.py
ratingcurve/tests/test_data.py
ratingcurve/tests/test_fitting.py
ratingcurve/tests/test_transform.py
ratingcurve-1.0.2.dist-info/LICENSE.md
ratingcurve-1.0.2.dist-info/METADATA
ratingcurve-1.0.2.dist-info/WHEEL
ratingcurve-1.0.2.dist-info/top_level.txt
ratingcurve-1.0.2.dist-info/RECORD
