Metadata-Version: 2.1
Name: ratingcurve
Version: 1.0.2
Summary: A library for fitting multi-segment stage-discharge rating curves.
Maintainer-email: Timothy Hodson <thodson@usgs.gov>
License: License
Project-URL: homepage, https://github.com/thodson-usgs/ratingcurve
Project-URL: repository, https://github.com/thodson-usgs/ratingcurve.git
Keywords: USGS,streamflow,rating curve
Classifier: Programming Language :: Python :: 3
Requires-Python: >=3.10
License-File: LICENSE.md
Requires-Dist: pymc >=5.0.0
Requires-Dist: patsy
Provides-Extra: test
Requires-Dist: pytest >5.0.0 ; extra == 'test'
Requires-Dist: pytest-cov[all] ; extra == 'test'
